pydantic_to_flat_dict_and_back/__init__.py
pydantic_to_flat_dict_and_back/src.py
pydantic_to_flat_dict_and_back-1.0.0.dist-info/METADATA
pydantic_to_flat_dict_and_back-1.0.0.dist-info/WHEEL
pydantic_to_flat_dict_and_back-1.0.0.dist-info/RECORD
