Metadata-Version: 2.1
Name: pydantic_to_flat_dict_and_back
Version: 1.0.0
Summary: Convert nested Pydantic models to flat dictionaries and back
Home-page: https://github.com/jogala/pydantic_to_flat_dict_and_back
License: MIT
Keywords: pydantic,flatten,dictionary,nested,conversion
Author: Joachim Rosenberger
Author-email: joachim.h.rosenberger@gmail.com
Requires-Python: >=3.12,<3.13
Classifier: Development Status :: 4 - Beta
Classifier: Intended Audience :: Developers
Classifier: License :: OSI Approved :: MIT License
Classifier: Programming Language :: Python :: 3
Classifier: Programming Language :: Python :: 3.12
Classifier: Topic :: Software Development :: Libraries :: Python Modules
Requires-Dist: pydantic (>=2.6.1,<2.7.0)
Project-URL: Repository, https://github.com/jogala/pydantic_to_flat_dict_and_back
